pjbcma/__init__.py
pjbcma/pjbcma.py
pjbcma_icushman-0.0.7.dist-info/LICENSE
pjbcma_icushman-0.0.7.dist-info/METADATA
pjbcma_icushman-0.0.7.dist-info/WHEEL
pjbcma_icushman-0.0.7.dist-info/top_level.txt
pjbcma_icushman-0.0.7.dist-info/RECORD
