Metadata-Version: 2.1
Name: pjbcma-icushman
Version: 0.0.7
Summary: An assistant for using pyjags
Home-page: https://github.com/icushman/pjBCM
Author: Isaiah Cushman
Author-email: icushman@uci.edu
License: UNKNOWN
Platform: UNKNOWN
Classifier: Programming Language :: Python :: 3
Classifier: License :: OSI Approved :: MIT License
Classifier: Operating System :: POSIX :: Linux
Requires-Dist: numpy
Requires-Dist: pyjags
Requires-Dist: pandas
Requires-Dist: matplotlib
Requires-Dist: seaborn
Requires-Dist: scipy
